{
  "name": "Dale Brooks",
  "age": 34,
  "address": {
    "street": "Hofomo Center",
    "city": "Azdojdu",
    "state": "DC",
    "zip": "27832"
  },
  "contact": {
    "phone": "(785) 616-7528",
    "servicePhone": "800125963"
  },
  "birthday": "1972-01-19T20:59:04.848Z",
  "ip": "192.135.147.237",
  "foo": "bar",
  "profile": {
    "about": "Misuk coapit fu hodofmer idbet zo liwvuj olapuc usza hofpopka kun nelwoj. Jothut jewtidfob bumetbe jogjodi tij nuwopsib ji lu cik kudfel fupadlov ha rufgetfu itu ucsek siuwdas fumfa. Bov coja ba nadiram hacultel nuj saovu igmi wer lek ca vifbabah ize viteb ezpud mifohir. Ziti zunlaapa kod ewu uzgurfo fobmiknef picuf su lif vod zeotu riv sazgun lakala no. Pivebik cowvin bonad kigadni rotu jakgaeco nab azge maar lab lutejde ab onafocur jud. Rome zupkume moafupa wopgos go ecebuw lomhergit evba lirum lunup ivoriim iwwukka ogrewwu haklan igauju.",
    "bio": "Jewahsu jamrinjo omi ibvarok zubuwi vosnag calibiken kagavji gif rog ajafa vobirbum osiomese. Fidukne daobaeh po de wedbad secinuk tut hihfuwtu gez zaldu gupazem zameho igen. Hefa je be kehifuv uvoni jejkamup sik tigzo har zogikde zeofu ukgowe duza de cuwgekjaz azpi. Ugaemo vow dusac ozru cucraodi ciirme kobo wipu usewejdur hetiswo pudwah mipipa bi vijo. Uriulibeb dutduzet huto zogku nigen erumufti weuni haccopme urbiacu rancu loj caeda habo jauc."
  },
  "apiKey": "d6f5b6cf9336f175f3c31ffdc9b1ed1f3eef3a1e9f1de1523c7bed825794b366",
  "currency": {
    "code": "XPF",
    "name": "Comptoirs Français du Pacifique (CFP) Franc"
  }
}