{
  "name": "Sylvia Reynolds",
  "age": 49,
  "address": {
    "street": "Zedow Street",
    "city": "Togaala",
    "state": "AL",
    "zip": "79685"
  },
  "contact": {
    "phone": "(634) 776-6081",
    "servicePhone": "800121851"
  },
  "birthday": "1998-08-23T20:28:17.150Z",
  "ip": "106.23.120.75",
  "foo": "bar",
  "profile": {
    "about": "Ummonad osbi saso zogo zufdebuh zibnodeg hi jedop neoba lu uboku oticac. Fumcuusu lilesi tuiju at dice ikifiv dig sep giznupzo zec kejovof luv vo pagasa je. Zu dehge fufe cuvva ajcu ihibije vojufne gut olikodel meh ojezu cabega sibac.",
    "bio": "Cegcep ofuabo jetseagu ubogigu kagkag ki obazuhzep pebbocone nefukzeg gipu awurirro cemkod kek. Jeduwena verekaf ombih venelefo ugabo dak umi kabtimgu ebo zih damholpi fovahip. Beida naubcuj hurkaz asolaavo wugja sume cu folga sekbecus melzuket facbesi lo zuzozif oje zafobi it. Fi eno fege pavged tohav mawo hibo tegcatlih giguluzu avaef jugzoip ihiruh novocu akikow hetele. Cusboug itfopfa wocina va lagne mevu ege korovlon kukgu rawaov sa awra sovohah alpukuh ri tolus vumojke wizpos. Nokogaw guv nu teico gijeega or ji ibivar cersadva pub hagpun ivujebom ep caskahod eci ucrut."
  },
  "apiKey": "8db14896cada6ad66612e22a10d36363ef1532a1c290ba142a6a44fa5c465fb9",
  "currency": {
    "code": "MUR",
    "name": "Mauritius Rupee"
  }
}